{
  "assets": [
    {
      "id": "12345678-1234-1234-1234-123456789001",
      "has_agent": true,
      "has_plugin_results": true,
      "created_at": "2024-01-15T10:30:00.000Z",
      "updated_at": "2024-06-13T14:22:15.000Z",
      "first_seen": "2024-01-15T10:30:00.000Z",
      "last_seen": "2024-06-13T14:22:15.000Z",
      "hostname": "dc01.enterprise.local",
      "fqdn": ["dc01.enterprise.local", "dc01.corp.local"],
      "netbios_name": "DC01",
      "operating_system": ["Windows Server 2019 Standard"],
      "system_type": ["domain-controller"],
      "ipv4": ["10.0.1.10"],
      "mac_address": ["00:50:56:a1:b2:c3"],
      "tags": [
        {"key": "Environment", "value": "Production"},
        {"key": "Role", "value": "Domain Controller"},
        {"key": "Criticality", "value": "Critical"}
      ],
      "exposure_score": 950,
      "acr_score": 9.5,
      "criticality_rating": "critical"
    },
    {
      "id": "12345678-1234-1234-1234-123456789002",
      "has_agent": true,
      "has_plugin_results": true,
      "created_at": "2024-01-16T08:15:00.000Z",
      "updated_at": "2024-06-13T12:45:30.000Z",
      "first_seen": "2024-01-16T08:15:00.000Z",
      "last_seen": "2024-06-13T12:45:30.000Z",
      "hostname": "web01.enterprise.local",
      "fqdn": ["web01.enterprise.local", "www.enterprise.com"],
      "netbios_name": "WEB01",
      "operating_system": ["Ubuntu Server 22.04.3 LTS"],
      "system_type": ["web-server"],
      "ipv4": ["10.0.2.100", "203.0.113.45"],
      "mac_address": ["00:50:56:a2:b3:c4"],
      "tags": [
        {"key": "Environment", "value": "Production"},
        {"key": "Role", "value": "Web Server"},
        {"key": "Criticality", "value": "High"}
      ],
      "exposure_score": 780,
      "acr_score": 8.2,
      "criticality_rating": "high"
    },
    {
      "id": "12345678-1234-1234-1234-123456789003",
      "has_agent": true,
      "has_plugin_results": true,
      "created_at": "2024-01-18T14:20:00.000Z",
      "updated_at": "2024-06-13T16:10:45.000Z",
      "first_seen": "2024-01-18T14:20:00.000Z",
      "last_seen": "2024-06-13T16:10:45.000Z",
      "hostname": "db01.enterprise.local",
      "fqdn": ["db01.enterprise.local"],
      "netbios_name": "DB01",
      "operating_system": ["Red Hat Enterprise Linux 8.6"],
      "system_type": ["database-server"],
      "ipv4": ["10.0.3.50"],
      "mac_address": ["00:50:56:a3:b4:c5"],
      "tags": [
        {"key": "Environment", "value": "Production"},
        {"key": "Role", "value": "Database Server"},
        {"key": "Criticality", "value": "Critical"}
      ],
      "exposure_score": 890,
      "acr_score": 9.1,
      "criticality_rating": "critical"
    },
    {
      "id": "12345678-1234-1234-1234-123456789004",
      "has_agent": false,
      "has_plugin_results": true,
      "created_at": "2024-02-01T09:30:00.000Z",
      "updated_at": "2024-06-13T11:20:15.000Z",
      "first_seen": "2024-02-01T09:30:00.000Z",
      "last_seen": "2024-06-13T11:20:15.000Z",
      "hostname": "fw01.enterprise.local",
      "fqdn": ["fw01.enterprise.local"],
      "netbios_name": "FW01",
      "operating_system": ["Cisco ASA 9.16"],
      "system_type": ["firewall"],
      "ipv4": ["10.0.0.1", "203.0.113.1"],
      "mac_address": ["00:1a:2b:3c:4d:5e"],
      "tags": [
        {"key": "Environment", "value": "Production"},
        {"key": "Role", "value": "Firewall"},
        {"key": "Criticality", "value": "High"}
      ],
      "exposure_score": 650,
      "acr_score": 7.8,
      "criticality_rating": "high"
    },
    {
      "id": "12345678-1234-1234-1234-123456789005",
      "has_agent": true,
      "has_plugin_results": true,
      "created_at": "2024-02-05T13:45:00.000Z",
      "updated_at": "2024-06-13T09:35:20.000Z",
      "first_seen": "2024-02-05T13:45:00.000Z",
      "last_seen": "2024-06-13T09:35:20.000Z",
      "hostname": "mail01.enterprise.local",
      "fqdn": ["mail01.enterprise.local", "mail.enterprise.com"],
      "netbios_name": "MAIL01",
      "operating_system": ["Windows Server 2022 Standard"],
      "system_type": ["mail-server"],
      "ipv4": ["10.0.4.25"],
      "mac_address": ["00:50:56:a4:b5:c6"],
      "tags": [
        {"key": "Environment", "value": "Production"},
        {"key": "Role", "value": "Mail Server"},
        {"key": "Criticality", "value": "High"}
      ],
      "exposure_score": 720,
      "acr_score": 8.0,
      "criticality_rating": "high"
    },
    {
      "id": "12345678-1234-1234-1234-123456789006",
      "has_agent": true,
      "has_plugin_results": true,
      "created_at": "2024-02-10T11:15:00.000Z",
      "updated_at": "2024-06-13T15:50:30.000Z",
      "first_seen": "2024-02-10T11:15:00.000Z",
      "last_seen": "2024-06-13T15:50:30.000Z",
      "hostname": "fs01.enterprise.local",
      "fqdn": ["fs01.enterprise.local"],
      "netbios_name": "FS01",
      "operating_system": ["Windows Server 2019 Standard"],
      "system_type": ["file-server"],
      "ipv4": ["10.0.5.30"],
      "mac_address": ["00:50:56:a5:b6:c7"],
      "tags": [
        {"key": "Environment", "value": "Production"},
        {"key": "Role", "value": "File Server"},
        {"key": "Criticality", "value": "Medium"}
      ],
      "exposure_score": 580,
      "acr_score": 6.5,
      "criticality_rating": "medium"
    },
    {
      "id": "12345678-1234-1234-1234-123456789007",
      "has_agent": true,
      "has_plugin_results": true,
      "created_at": "2024-02-15T16:30:00.000Z",
      "updated_at": "2024-06-13T13:25:45.000Z",
      "first_seen": "2024-02-15T16:30:00.000Z",
      "last_seen": "2024-06-13T13:25:45.000Z",
      "hostname": "app01.enterprise.local",
      "fqdn": ["app01.enterprise.local", "apps.enterprise.com"],
      "netbios_name": "APP01",
      "operating_system": ["CentOS Linux 7.9"],
      "system_type": ["application-server"],
      "ipv4": ["10.0.6.40"],
      "mac_address": ["00:50:56:a6:b7:c8"],
      "tags": [
        {"key": "Environment", "value": "Production"},
        {"key": "Role", "value": "Application Server"},
        {"key": "Criticality", "value": "High"}
      ],
      "exposure_score": 740,
      "acr_score": 7.9,
      "criticality_rating": "high"
    },
    {
      "id": "12345678-1234-1234-1234-123456789008",
      "has_agent": false,
      "has_plugin_results": true,
      "created_at": "2024-02-20T10:45:00.000Z",
      "updated_at": "2024-06-13T14:40:15.000Z",
      "first_seen": "2024-02-20T10:45:00.000Z",
      "last_seen": "2024-06-13T14:40:15.000Z",
      "hostname": "switch01.enterprise.local",
      "fqdn": ["switch01.enterprise.local"],
      "netbios_name": "SW01",
      "operating_system": ["Cisco IOS 15.2"],
      "system_type": ["network-switch"],
      "ipv4": ["10.0.0.10"],
      "mac_address": ["00:1b:2c:3d:4e:5f"],
      "tags": [
        {"key": "Environment", "value": "Production"},
        {"key": "Role", "value": "Network Switch"},
        {"key": "Criticality", "value": "Medium"}
      ],
      "exposure_score": 450,
      "acr_score": 5.8,
      "criticality_rating": "medium"
    },
    {
      "id": "12345678-1234-1234-1234-123456789009",
      "has_agent": true,
      "has_plugin_results": true,
      "created_at": "2024-03-01T08:20:00.000Z",
      "updated_at": "2024-06-13T10:15:30.000Z",
      "first_seen": "2024-03-01T08:20:00.000Z",
      "last_seen": "2024-06-13T10:15:30.000Z",
      "hostname": "backup01.enterprise.local",
      "fqdn": ["backup01.enterprise.local"],
      "netbios_name": "BACKUP01",
      "operating_system": ["Windows Server 2022 Standard"],
      "system_type": ["backup-server"],
      "ipv4": ["10.0.7.20"],
      "mac_address": ["00:50:56:a7:b8:c9"],
      "tags": [
        {"key": "Environment", "value": "Production"},
        {"key": "Role", "value": "Backup Server"},
        {"key": "Criticality", "value": "Medium"}
      ],
      "exposure_score": 520,
      "acr_score": 6.2,
      "criticality_rating": "medium"
    },
    {
      "id": "12345678-1234-1234-1234-123456789010",
      "has_agent": true,
      "has_plugin_results": true,
      "created_at": "2024-03-05T12:30:00.000Z",
      "updated_at": "2024-06-13T08:45:20.000Z",
      "first_seen": "2024-03-05T12:30:00.000Z",
      "last_seen": "2024-06-13T08:45:20.000Z",
      "hostname": "vpn01.enterprise.local",
      "fqdn": ["vpn01.enterprise.local", "vpn.enterprise.com"],
      "netbios_name": "VPN01",
      "operating_system": ["Ubuntu Server 20.04.6 LTS"],
      "system_type": ["vpn-server"],
      "ipv4": ["10.0.8.15", "203.0.113.100"],
      "mac_address": ["00:50:56:a8:b9:ca"],
      "tags": [
        {"key": "Environment", "value": "Production"},
        {"key": "Role", "value": "VPN Server"},
        {"key": "Criticality", "value": "High"}
      ],
      "exposure_score": 680,
      "acr_score": 7.5,
      "criticality_rating": "high"
    },
    {
      "id": "12345678-1234-1234-1234-123456789011",
      "has_agent": true,
      "has_plugin_results": true,
      "created_at": "2024-03-10T14:45:00.000Z",
      "updated_at": "2024-06-13T12:30:45.000Z",
      "first_seen": "2024-03-10T14:45:00.000Z",
      "last_seen": "2024-06-13T12:30:45.000Z",
      "hostname": "monitor01.enterprise.local",
      "fqdn": ["monitor01.enterprise.local"],
      "netbios_name": "MON01",
      "operating_system": ["CentOS Linux 8.5"],
      "system_type": ["monitoring-server"],
      "ipv4": ["10.0.9.35"],
      "mac_address": ["00:50:56:a9:ba:cb"],
      "tags": [
        {"key": "Environment", "value": "Production"},
        {"key": "Role", "value": "Monitoring Server"},
        {"key": "Criticality", "value": "Medium"}
      ],
      "exposure_score": 490,
      "acr_score": 5.9,
      "criticality_rating": "medium"
    },
    {
      "id": "12345678-1234-1234-1234-123456789012",
      "has_agent": true,
      "has_plugin_results": true,
      "created_at": "2024-03-15T09:15:00.000Z",
      "updated_at": "2024-06-13T16:20:15.000Z",
      "first_seen": "2024-03-15T09:15:00.000Z",
      "last_seen": "2024-06-13T16:20:15.000Z",
      "hostname": "dns01.enterprise.local",
      "fqdn": ["dns01.enterprise.local"],
      "netbios_name": "DNS01",
      "operating_system": ["Windows Server 2019 Standard"],
      "system_type": ["dns-server"],
      "ipv4": ["10.0.1.53"],
      "mac_address": ["00:50:56:aa:bb:cc"],
      "tags": [
        {"key": "Environment", "value": "Production"},
        {"key": "Role", "value": "DNS Server"},
        {"key": "Criticality", "value": "High"}
      ],
      "exposure_score": 710,
      "acr_score": 7.8,
      "criticality_rating": "high"
    },
    {
      "id": "12345678-1234-1234-1234-123456789013",
      "has_agent": true,
      "has_plugin_results": true,
      "created_at": "2024-03-20T11:30:00.000Z",
      "updated_at": "2024-06-13T14:55:30.000Z",
      "first_seen": "2024-03-20T11:30:00.000Z",
      "last_seen": "2024-06-13T14:55:30.000Z",
      "hostname": "print01.enterprise.local",
      "fqdn": ["print01.enterprise.local"],
      "netbios_name": "PRINT01",
      "operating_system": ["Windows Server 2016 Standard"],
      "system_type": ["print-server"],
      "ipv4": ["10.0.10.45"],
      "mac_address": ["00:50:56:ab:bc:cd"],
      "tags": [
        {"key": "Environment", "value": "Production"},
        {"key": "Role", "value": "Print Server"},
        {"key": "Criticality", "value": "Low"}
      ],
      "exposure_score": 380,
      "acr_score": 4.5,
      "criticality_rating": "low"
    },
    {
      "id": "12345678-1234-1234-1234-123456789014",
      "has_agent": true,
      "has_plugin_results": true,
      "created_at": "2024-03-25T13:45:00.000Z",
      "updated_at": "2024-06-13T09:40:45.000Z",
      "first_seen": "2024-03-25T13:45:00.000Z",
      "last_seen": "2024-06-13T09:40:45.000Z",
      "hostname": "test-web01.enterprise.local",
      "fqdn": ["test-web01.enterprise.local"],
      "netbios_name": "TESTWEB01",
      "operating_system": ["Ubuntu Server 22.04.3 LTS"],
      "system_type": ["test-server"],
      "ipv4": ["10.0.11.100"],
      "mac_address": ["00:50:56:ac:bd:ce"],
      "tags": [
        {"key": "Environment", "value": "Testing"},
        {"key": "Role", "value": "Test Web Server"},
        {"key": "Criticality", "value": "Low"}
      ],
      "exposure_score": 420,
      "acr_score": 5.1,
      "criticality_rating": "low"
    },
    {
      "id": "12345678-1234-1234-1234-123456789015",
      "has_agent": true,
      "has_plugin_results": true,
      "created_at": "2024-04-01T10:00:00.000Z",
      "updated_at": "2024-06-13T15:15:20.000Z",
      "first_seen": "2024-04-01T10:00:00.000Z",
      "last_seen": "2024-06-13T15:15:20.000Z",
      "hostname": "dev-db01.enterprise.local",
      "fqdn": ["dev-db01.enterprise.local"],
      "netbios_name": "DEVDB01",
      "operating_system": ["Red Hat Enterprise Linux 9.2"],
      "system_type": ["development-server"],
      "ipv4": ["10.0.12.50"],
      "mac_address": ["00:50:56:ad:be:cf"],
      "tags": [
        {"key": "Environment", "value": "Development"},
        {"key": "Role", "value": "Development Database"},
        {"key": "Criticality", "value": "Low"}
      ],
      "exposure_score": 390,
      "acr_score": 4.8,
      "criticality_rating": "low"
    },
    {
      "id": "12345678-1234-1234-1234-123456789016",
      "has_agent": false,
      "has_plugin_results": true,
      "created_at": "2024-04-05T15:20:00.000Z",
      "updated_at": "2024-06-13T11:30:40.000Z",
      "first_seen": "2024-04-05T15:20:00.000Z",
      "last_seen": "2024-06-13T11:30:40.000Z",
      "hostname": "192.168.1.100",
      "fqdn": [],
      "netbios_name": "",
      "operating_system": ["Unknown"],
      "system_type": ["unknown"],
      "ipv4": ["192.168.1.100"],
      "mac_address": ["00:1c:2d:3e:4f:60"],
      "tags": [
        {"key": "Environment", "value": "Unknown"},
        {"key": "Role", "value": "Unidentified Device"},
        {"key": "Criticality", "value": "Medium"}
      ],
      "exposure_score": 600,
      "acr_score": 6.8,
      "criticality_rating": "medium"
    },
    {
      "id": "12345678-1234-1234-1234-123456789017",
      "has_agent": true,
      "has_plugin_results": true,
      "created_at": "2024-04-10T08:45:00.000Z",
      "updated_at": "2024-06-13T13:50:25.000Z",
      "first_seen": "2024-04-10T08:45:00.000Z",
      "last_seen": "2024-06-13T13:50:25.000Z",
      "hostname": "citrix01.enterprise.local",
      "fqdn": ["citrix01.enterprise.local", "remote.enterprise.com"],
      "netbios_name": "CITRIX01",
      "operating_system": ["Windows Server 2019 Standard"],
      "system_type": ["terminal-server"],
      "ipv4": ["10.0.13.75"],
      "mac_address": ["00:50:56:ae:bf:d0"],
      "tags": [
        {"key": "Environment", "value": "Production"},
        {"key": "Role", "value": "Terminal Server"},
        {"key": "Criticality", "value": "High"}
      ],
      "exposure_score": 760,
      "acr_score": 8.1,
      "criticality_rating": "high"
    },
    {
      "id": "12345678-1234-1234-1234-123456789018",
      "has_agent": true,
      "has_plugin_results": true,
      "created_at": "2024-04-15T12:15:00.000Z",
      "updated_at": "2024-06-13T10:45:50.000Z",
      "first_seen": "2024-04-15T12:15:00.000Z",
      "last_seen": "2024-06-13T10:45:50.000Z",
      "hostname": "proxy01.enterprise.local",
      "fqdn": ["proxy01.enterprise.local"],
      "netbios_name": "PROXY01",
      "operating_system": ["Ubuntu Server 20.04.6 LTS"],
      "system_type": ["proxy-server"],
      "ipv4": ["10.0.14.80"],
      "mac_address": ["00:50:56:af:c0:d1"],
      "tags": [
        {"key": "Environment", "value": "Production"},
        {"key": "Role", "value": "Proxy Server"},
        {"key": "Criticality", "value": "Medium"}
      ],
      "exposure_score": 540,
      "acr_score": 6.4,
      "criticality_rating": "medium"
    },
    {
      "id": "12345678-1234-1234-1234-123456789019",
      "has_agent": true,
      "has_plugin_results": true,
      "created_at": "2024-04-20T14:30:00.000Z",
      "updated_at": "2024-06-13T16:25:35.000Z",
      "first_seen": "2024-04-20T14:30:00.000Z",
      "last_seen": "2024-06-13T16:25:35.000Z",
      "hostname": "ntp01.enterprise.local",
      "fqdn": ["ntp01.enterprise.local"],
      "netbios_name": "NTP01",
      "operating_system": ["CentOS Linux 7.9"],
      "system_type": ["time-server"],
      "ipv4": ["10.0.15.123"],
      "mac_address": ["00:50:56:b0:c1:d2"],
      "tags": [
        {"key": "Environment", "value": "Production"},
        {"key": "Role", "value": "Time Server"},
        {"key": "Criticality", "value": "Low"}
      ],
      "exposure_score": 320,
      "acr_score": 4.2,
      "criticality_rating": "low"
    },
    {
      "id": "12345678-1234-1234-1234-123456789020",
      "has_agent": true,
      "has_plugin_results": true,
      "created_at": "2024-04-25T09:45:00.000Z",
      "updated_at": "2024-06-13T12:10:15.000Z",
      "first_seen": "2024-04-25T09:45:00.000Z",
      "last_seen": "2024-06-13T12:10:15.000Z",
      "hostname": "log01.enterprise.local",
      "fqdn": ["log01.enterprise.local"],
      "netbios_name": "LOG01",
      "operating_system": ["Red Hat Enterprise Linux 8.6"],
      "system_type": ["logging-server"],
      "ipv4": ["10.0.16.200"],
      "mac_address": ["00:50:56:b1:c2:d3"],
      "tags": [
        {"key": "Environment", "value": "Production"},
        {"key": "Role", "value": "Log Server"},
        {"key": "Criticality", "value": "Medium"}
      ],
      "exposure_score": 510,
      "acr_score": 6.1,
      "criticality_rating": "medium"
    },
    {
      "id": "12345678-1234-1234-1234-123456789021",
      "has_agent": true,
      "has_plugin_results": true,
      "created_at": "2024-05-01T11:00:00.000Z",
      "updated_at": "2024-06-13T14:35:40.000Z",
      "first_seen": "2024-05-01T11:00:00.000Z",
      "last_seen": "2024-06-13T14:35:40.000Z",
      "hostname": "wsus01.enterprise.local",
      "fqdn": ["wsus01.enterprise.local"],
      "netbios_name": "WSUS01",
      "operating_system": ["Windows Server 2022 Standard"],
      "system_type": ["update-server"],
      "ipv4": ["10.0.17.150"],
      "mac_address": ["00:50:56:b2:c3:d4"],
      "tags": [
        {"key": "Environment", "value": "Production"},
        {"key": "Role", "value": "Update Server"},
        {"key": "Criticality", "value": "Medium"}
      ],
      "exposure_score": 480,
      "acr_score": 5.7,
      "criticality_rating": "medium"
    },
    {
      "id": "12345678-1234-1234-1234-123456789022",
      "has_agent": true,
      "has_plugin_results": true,
      "created_at": "2024-05-05T13:20:00.000Z",
      "updated_at": "2024-06-13T08:50:25.000Z",
      "first_seen": "2024-05-05T13:20:00.000Z",
      "last_seen": "2024-06-13T08:50:25.000Z",
      "hostname": "antivirus01.enterprise.local",
      "fqdn": ["antivirus01.enterprise.local"],
      "netbios_name": "AV01",
      "operating_system": ["Windows Server 2019 Standard"],
      "system_type": ["security-server"],
      "ipv4": ["10.0.18.110"],
      "mac_address": ["00:50:56:b3:c4:d5"],
      "tags": [
        {"key": "Environment", "value": "Production"},
        {"key": "Role", "value": "Antivirus Server"},
        {"key": "Criticality", "value": "Medium"}
      ],
      "exposure_score": 560,
      "acr_score": 6.6,
      "criticality_rating": "medium"
    },
    {
      "id": "12345678-1234-1234-1234-123456789023",
      "has_agent": false,
      "has_plugin_results": true,
      "created_at": "2024-05-10T10:35:00.000Z",
      "updated_at": "2024-06-13T15:40:30.000Z",
      "first_seen": "2024-05-10T10:35:00.000Z",
      "last_seen": "2024-06-13T15:40:30.000Z",
      "hostname": "ups01.enterprise.local",
      "fqdn": ["ups01.enterprise.local"],
      "netbios_name": "",
      "operating_system": ["APC Network Management Card"],
      "system_type": ["ups"],
      "ipv4": ["10.0.19.250"],
      "mac_address": ["00:c0:b7:12:34:56"],
      "tags": [
        {"key": "Environment", "value": "Production"},
        {"key": "Role", "value": "UPS"},
        {"key": "Criticality", "value": "Low"}
      ],
      "exposure_score": 280,
      "acr_score": 3.8,
      "criticality_rating": "low"
    },
    {
      "id": "12345678-1234-1234-1234-123456789024",
      "has_agent": true,
      "has_plugin_results": true,
      "created_at": "2024-05-15T12:50:00.000Z",
      "updated_at": "2024-06-13T11:15:45.000Z",
      "first_seen": "2024-05-15T12:50:00.000Z",
      "last_seen": "2024-06-13T11:15:45.000Z",
      "hostname": "erp01.enterprise.local",
      "fqdn": ["erp01.enterprise.local", "erp.enterprise.com"],
      "netbios_name": "ERP01",
      "operating_system": ["Windows Server 2022 Standard"],
      "system_type": ["erp-server"],
      "ipv4": ["10.0.20.100"],
      "mac_address": ["00:50:56:b4:c5:d6"],
      "tags": [
        {"key": "Environment", "value": "Production"},
        {"key": "Role", "value": "ERP Server"},
        {"key": "Criticality", "value": "Critical"}
      ],
      "exposure_score": 920,
      "acr_score": 9.3,
      "criticality_rating": "critical"
    },
    {
      "id": "12345678-1234-1234-1234-123456789025",
      "has_agent": true,
      "has_plugin_results": true,
      "created_at": "2024-05-20T15:10:00.000Z",
      "updated_at": "2024-06-13T13:20:50.000Z",
      "first_seen": "2024-05-20T15:10:00.000Z",
      "last_seen": "2024-06-13T13:20:50.000Z",
      "hostname": "crm01.enterprise.local",
      "fqdn": ["crm01.enterprise.local", "crm.enterprise.com"],
      "netbios_name": "CRM01",
      "operating_system": ["Ubuntu Server 22.04.3 LTS"],
      "system_type": ["crm-server"],
      "ipv4": ["10.0.21.75"],
      "mac_address": ["00:50:56:b5:c6:d7"],
      "tags": [
        {"key": "Environment", "value": "Production"},
        {"key": "Role", "value": "CRM Server"},
        {"key": "Criticality", "value": "High"}
      ],
      "exposure_score": 790,
      "acr_score": 8.4,
      "criticality_rating": "high"
    },
    {
      "id": "12345678-1234-1234-1234-123456789026",
      "has_agent": true,
      "has_plugin_results": true,
      "created_at": "2024-05-25T08:25:00.000Z",
      "updated_at": "2024-06-13T16:45:20.000Z",
      "first_seen": "2024-05-25T08:25:00.000Z",
      "last_seen": "2024-06-13T16:45:20.000Z",
      "hostname": "hr01.enterprise.local",
      "fqdn": ["hr01.enterprise.local"],
      "netbios_name": "HR01",
      "operating_system": ["Windows Server 2019 Standard"],
      "system_type": ["hr-server"],
      "ipv4": ["10.0.22.60"],
      "mac_address": ["00:50:56:b6:c7:d8"],
      "tags": [
        {"key": "Environment", "value": "Production"},
        {"key": "Role", "value": "HR Server"},
        {"key": "Criticality", "value": "High"}
      ],
      "exposure_score": 730,
      "acr_score": 7.7,
      "criticality_rating": "high"
    },
    {
      "id": "12345678-1234-1234-1234-123456789027",
      "has_agent": true,
      "has_plugin_results": true,
      "created_at": "2024-05-30T10:40:00.000Z",
      "updated_at": "2024-06-13T09:30:35.000Z",
      "first_seen": "2024-05-30T10:40:00.000Z",
      "last_seen": "2024-06-13T09:30:35.000Z",
      "hostname": "finance01.enterprise.local",
      "fqdn": ["finance01.enterprise.local"],
      "netbios_name": "FIN01",
      "operating_system": ["Red Hat Enterprise Linux 9.2"],
      "system_type": ["finance-server"],
      "ipv4": ["10.0.23.45"],
      "mac_address": ["00:50:56:b7:c8:d9"],
      "tags": [
        {"key": "Environment", "value": "Production"},
        {"key": "Role", "value": "Finance Server"},
        {"key": "Criticality", "value": "Critical"}
      ],
      "exposure_score": 880,
      "acr_score": 9.0,
      "criticality_rating": "critical"
    },
    {
      "id": "12345678-1234-1234-1234-123456789028",
      "has_agent": true,
      "has_plugin_results": true,
      "created_at": "2024-06-01T14:15:00.000Z",
      "updated_at": "2024-06-13T12:55:40.000Z",
      "first_seen": "2024-06-01T14:15:00.000Z",
      "last_seen": "2024-06-13T12:55:40.000Z",
      "hostname": "bi01.enterprise.local",
      "fqdn": ["bi01.enterprise.local", "analytics.enterprise.com"],
      "netbios_name": "BI01",
      "operating_system": ["Windows Server 2022 Standard"],
      "system_type": ["analytics-server"],
      "ipv4": ["10.0.24.90"],
      "mac_address": ["00:50:56:b8:c9:da"],
      "tags": [
        {"key": "Environment", "value": "Production"},
        {"key": "Role", "value": "Business Intelligence"},
        {"key": "Criticality", "value": "Medium"}
      ],
      "exposure_score": 620,
      "acr_score": 7.1,
      "criticality_rating": "medium"
    },
    {
      "id": "12345678-1234-1234-1234-123456789029",
      "has_agent": true,
      "has_plugin_results": true,
      "created_at": "2024-06-05T16:30:00.000Z",
      "updated_at": "2024-06-13T14:20:25.000Z",
      "first_seen": "2024-06-05T16:30:00.000Z",
      "last_seen": "2024-06-13T14:20:25.000Z",
      "hostname": "staging01.enterprise.local",
      "fqdn": ["staging01.enterprise.local"],
      "netbios_name": "STAGE01",
      "operating_system": ["Ubuntu Server 22.04.3 LTS"],
      "system_type": ["staging-server"],
      "ipv4": ["10.0.25.120"],
      "mac_address": ["00:50:56:b9:ca:db"],
      "tags": [
        {"key": "Environment", "value": "Staging"},
        {"key": "Role", "value": "Staging Server"},
        {"key": "Criticality", "value": "Low"}
      ],
      "exposure_score": 450,
      "acr_score": 5.3,
      "criticality_rating": "low"
    },
    {
      "id": "12345678-1234-1234-1234-123456789030",
      "has_agent": false,
      "has_plugin_results": true,
      "created_at": "2024-06-10T11:45:00.000Z",
      "updated_at": "2024-06-13T10:05:50.000Z",
      "first_seen": "2024-06-10T11:45:00.000Z",
      "last_seen": "2024-06-13T10:05:50.000Z",
      "hostname": "iot-sensor01.enterprise.local",
      "fqdn": [],
      "netbios_name": "",
      "operating_system": ["Embedded Linux"],
      "system_type": ["iot-device"],
      "ipv4": ["10.0.26.201"],
      "mac_address": ["00:1d:2e:3f:50:61"],
      "tags": [
        {"key": "Environment", "value": "Production"},
        {"key": "Role", "value": "IoT Sensor"},
        {"key": "Criticality", "value": "Low"}
      ],
      "exposure_score": 340,
      "acr_score": 4.1,
      "criticality_rating": "low"
    }
  ],
  "total": 30,
  "pagination": {
    "limit": 50,
    "offset": 0,
    "sort": [
      {
        "name": "criticality_rating",
        "order": "desc"
      }
    ]
  }
}